quota_tracker/__init__.py
quota_tracker/main.py
quota_tracker/options.py
quota_tracker/utils.py
quota_tracker-0.4.dist-info/METADATA
quota_tracker-0.4.dist-info/WHEEL
quota_tracker-0.4.dist-info/top_level.txt
quota_tracker-0.4.dist-info/RECORD
