Metadata-Version: 2.1
Name: quota-tracker
Version: 0.4
Summary: A quota tracker package
Home-page: https://github.com/thidang2901/quota-tracker
Author: Thi Dang
Author-email: dkthi2901@gmail.com
License: UNKNOWN
Project-URL: Bug Tracker, https://github.com/thidang2901/quota-tracker/issues
Platform: UNKNOWN
Classifier: Programming Language :: Python :: 3
Classifier: License :: OSI Approved :: MIT License
Classifier: Operating System :: OS Independent
Requires-Python: >=3.6
